[
  {
    "floor": 7,
    "people_got_out": [],
    "people_got_in": ["person-1", "person-2", "person-3", "person-4", "person-5", "person-10", "person-14"]
  },
  {
    "floor": 0,
    "people_got_out": ["person-1", "person-2", "person-3", "person-4", "person-5", "person-10"],
    "people_got_in": []
  },
  {
    "floor": 3,
    "people_got_out": ["person-14"],
    "people_got_in": []
  },
  {
    "floor": 7,
    "people_got_out": [],
    "people_got_in": ["person-6", "person-15", "person-16", "person-17", "person-18", "person-19", "person-20"]
  },
  {
    "floor": 4,
    "people_got_out": ["person-16", "person-19"],
    "people_got_in": []
  },
  {
    "floor": 5,
    "people_got_out": ["person-15"],
    "people_got_in": []
  },
  {
    "floor": 6,
    "people_got_out": ["person-18"],
    "people_got_in": []
  },
  {
    "floor": 8,
    "people_got_out": ["person-6", "person-17", "person-20"],
    "people_got_in": []
  },
  {
    "floor": 7,
    "people_got_out": [],
    "people_got_in": ["person-7", "person-8", "person-9", "person-11", "person-12", "person-13"]
  },
  {
    "floor": 2,
    "people_got_out": ["person-8", "person-9", "person-13"],
    "people_got_in": []
  },
  {
    "floor": 1,
    "people_got_out": ["person-7", "person-11", "person-12"],
    "people_got_in": []
  }
]

